projectmap/__init__.py
projectmap/visualizer.py
projectmap-0.1.2.dist-info/METADATA
projectmap-0.1.2.dist-info/WHEEL
projectmap-0.1.2.dist-info/entry_points.txt
projectmap-0.1.2.dist-info/licenses/LICENSE
projectmap-0.1.2.dist-info/RECORD
