Metadata-Version: 2.4
Name: projectmap
Version: 0.1.2
Summary: A modern tool for visualizing project structures in the terminal
Project-URL: Homepage, https://github.com/mr-akkerman/projectmap
Author-email: Ivan Akkerman <akakerman.live@gmail.com>
License: MIT License
License-File: LICENSE
Keywords: map,project,structure,tree,visualization
Classifier: License :: OSI Approved :: MIT License
Classifier: Programming Language :: Python
Classifier: Programming Language :: Python :: 3
Requires-Python: >=3.7
Provides-Extra: dev
Requires-Dist: pytest; extra == 'dev'
